ProGPT/Authentication.py
ProGPT/Conversation.py
ProGPT/Generative.py
ProGPT/__init__.py
ProGPT-1.0.5.dist-info/LICENSE.txt
ProGPT-1.0.5.dist-info/METADATA
ProGPT-1.0.5.dist-info/WHEEL
ProGPT-1.0.5.dist-info/top_level.txt
ProGPT-1.0.5.dist-info/RECORD
