Metadata-Version: 2.1
Name: ProGPT
Version: 1.0.5
Summary: ❄️ Python Package To Access GPT-3.5 Free Model
Home-page: https://github.com/diezo/progpt
Download-URL: https://github.com/diezo/progpt/archive/refs/tags/v1.0.5.tar.gz
Author: Deepak Soni
Author-email: sonniiii@outlook.com
License: MIT
Keywords: progpt,chatgpt,gpt-3.5,python-gpt,python-chatgpt,ai,generative-ai,chatgpt-ai,python-ai,python-generative-ai
Classifier: Development Status :: 5 - Production/Stable
Classifier: Intended Audience :: Developers
Classifier: Topic :: Software Development :: Build Tools
Classifier: License :: OSI Approved :: MIT License
Classifier: Programming Language :: Python :: 3
Classifier: Programming Language :: Python :: 3.10
License-File: LICENSE.txt
Requires-Dist: requests
Requires-Dist: selenium
